[
    {
        "name": "Headlights",
        "controls": [
            {
                "type": "Button",
                "icon": "numeric-0",
                "width": 6,
                "height": 6,
                "positions": [
                    {
                        "modes": {
                            "Parking": false,
                            "LowBeams": false
                        },
                        "style": "toggled"
                    }
                ]
            },
            {
                "type": "Button",
                "icon": "car-parking-lights",
                "width": 6,
                "height": 6,
                "positions": [
                    {
                        "modes": {
                            "Parking": true,
                            "LowBeams": false
                        },
                        "style": "toggled",
                        "color": "green"
                    }
                ]
            },
            {
                "type": "Button",
                "icon": "car-light-dimmed",
                "width": 12,
                "height": 6,
                "positions": [
                    {
                        "modes": {
                            "Parking": true,
                            "LowBeams": true
                        },
                        "style": "toggled",
                        "color": "green"
                    }
                ]
            }
        ]
    },
    {
        "name": "High beams",
        "controls": [
            {
                "type": "Button",
                "icon": "car-light-high",
                "width": 12,
                "height": 6,
                "positions": [
                    {
                        "modes": {
                            "HighBeams": false
                        }
                    },
                    {
                        "modes": {
                            "HighBeams": true
                        },
                        "style": "toggled",
                        "color": "blue"
                    }
                ]
            },
            {
                "type": "Button",
                "icon": "car-light-high",
                "width": 12,
                "height": 6,
                "positions": [
                    {
                        "modes": {
                            "FlashToPass": false
                        }
                    },
                    {
                        "type": "hold",
                        "modes": {
                            "FlashToPass": true
                        },
                        "style": "toggled",
                        "color": "blue"
                    }
                ]
            }
        ]
    },
    {
        "name": "Fog lights",
        "controls": [
            {
                "type": "Button",
                "icon": "car-light-fog",
                "round": true,
                "width": 6,
                "height": 6,
                "positions": [
                    {
                        "modes": {
                            "FogFront": false
                        }
                    },
                    {
                        "modes": {
                            "FogFront": true
                        },
                        "style": "toggled",
                        "color": "green"
                    }
                ]
            },
            {
                "type": "Button",
                "icon": "car-light-fog",
                "round": true,
                "width": 6,
                "height": 6,
                "positions": [
                    {
                        "modes": {
                            "FogRear": false
                        }
                    },
                    {
                        "modes": {
                            "FogRear": true
                        },
                        "style": "toggled",
                        "color": "yellow"
                    }
                ]
            }
        ]
    },
    {
        "name": "Blinkers",
        "controls": [
            {
                "type": "Button",
                "icon": "arrow-left-bold-outline",
                "round": true,
                "width": 6,
                "height": 6,
                "positions": [
                    {
                        "modes": {
                            "BlinkL": false
                        }
                    },
                    {
                        "modes": {
                            "BlinkL": true
                        },
                        "style": "toggled",
                        "color": "green"
                    }
                ]
            },
            {
                "type": "Button",
                "icon": "arrow-right-bold-outline",
                "round": true,
                "width": 6,
                "height": 6,
                "positions": [
                    {
                        "modes": {
                            "BlinkR": false
                        }
                    },
                    {
                        "modes": {
                            "BlinkR": true
                        },
                        "style": "toggled",
                        "color": "green"
                    }
                ]
            },
            {
                "type": "Button",
                "icon": "hazard-lights",
                "color": "red",
                "width": 12,
                "height": 6,
                "positions": [
                    {
                        "modes": {
                            "Hazards": false
                        }
                    },
                    {
                        "modes": {
                            "Hazards": true
                        },
                        "style": "toggled"
                    }
                ]
            }
        ]
    },
    {
        "name": "Brakes",
        "controls": [
            {
                "type": "Button",
                "icon": "car-brake-alert",
                "width": 12,
                "height": 6,
                "positions": [
                    {
                        "modes": {
                            "Brake": false
                        }
                    },
                    {
                        "type": "hold",
                        "modes": {
                            "Brake": true
                        },
                        "style": "toggled",
                        "color": "red"
                    }
                ]
            },
            {
                "type": "Button",
                "icon": "car-brake-abs",
                "width": 6,
                "height": 6,
                "positions": [
                    {
                        "modes": {
                            "ESS": false
                        }
                    },
                    {
                        "type": "hold",
                        "modes": {
                            "ESS": true
                        },
                        "style": "toggled",
                        "color": "red"
                    }
                ]
            },
            {
                "type": "Button",
                "icon": "car-shift-pattern",
                "width": 6,
                "height": 6,
                "positions": [
                    {
                        "modes": {
                            "Reverse": false
                        }
                    },
                    {
                        "modes": {
                            "Reverse": true
                        },
                        "style": "toggled"
                    }
                ]
            }
        ]
    }
]
